chad_ui/__init__.py
chad_ui/__main__.py
chad_ui/components/native/templates/cotton/button/index.html
chad_ui/components/native/templates/cotton/button_group/index.html
chad_ui/components/native/templates/cotton/button_group/separator.html
chad_ui/components/native/templates/cotton/checkbox/index.html
chad_ui/components/native/templates/cotton/label/index.html
chad_ui/components/native/templates/cotton/spinner/index.html
chad_ui/main.py
chad_ui-0.0.9.dist-info/METADATA
chad_ui-0.0.9.dist-info/WHEEL
chad_ui-0.0.9.dist-info/entry_points.txt
chad_ui-0.0.9.dist-info/licenses/LICENSE
chad_ui-0.0.9.dist-info/RECORD
