Metadata-Version: 2.4
Name: chad-ui
Version: 0.0.9
Summary: Cotton/HTMX/AlpineJS Django components in the style of shadcn/ui
License-File: LICENSE
Author: Maxim Belyayev
Author-email: maximbelyayev@gmail.com
Requires-Python: >=3.12
Classifier: Programming Language :: Python :: 3
Classifier: Programming Language :: Python :: 3.12
Classifier: Programming Language :: Python :: 3.13
Classifier: Programming Language :: Python :: 3.14
Requires-Dist: rich (>=14.2.0,<15.0.0)
